MANIFEST.in
README.md
pyproject.toml
setup.cfg
setup.py
baseapp_wagtail/__init__.py
baseapp_wagtail/apps.py
baseapp_wagtail/settings.py
baseapp_wagtail/urls.py
baseapp_wagtail.egg-info/PKG-INFO
baseapp_wagtail.egg-info/SOURCES.txt
baseapp_wagtail.egg-info/dependency_links.txt
baseapp_wagtail.egg-info/requires.txt
baseapp_wagtail.egg-info/top_level.txt
baseapp_wagtail/base/__init__.py
baseapp_wagtail/base/apps.py
baseapp_wagtail/base/models.py
baseapp_wagtail/base/wagtail_hooks.py
baseapp_wagtail/base/blocks/__init__.py
baseapp_wagtail/base/blocks/basic_blocks/__init__.py
baseapp_wagtail/base/blocks/basic_blocks/custom_image_block/__init__.py
baseapp_wagtail/base/blocks/basic_blocks/custom_image_block/block.py
baseapp_wagtail/base/blocks/basic_blocks/custom_image_chooser_block/__init__.py
baseapp_wagtail/base/blocks/basic_blocks/custom_image_chooser_block/block.py
baseapp_wagtail/base/blocks/basic_blocks/custom_rich_text_block/__init__.py
baseapp_wagtail/base/blocks/basic_blocks/custom_rich_text_block/block.py
baseapp_wagtail/base/blocks/custom_blocks/__init__.py
baseapp_wagtail/base/blocks/custom_blocks/banner_block/__init__.py
baseapp_wagtail/base/blocks/custom_blocks/banner_block/block.py
baseapp_wagtail/base/rest_framework/__init__.py
baseapp_wagtail/base/rest_framework/router.py
baseapp_wagtail/base/rest_framework/page_preview/__init__.py
baseapp_wagtail/base/rest_framework/page_preview/views.py
baseapp_wagtail/base/rest_framework/pages/__init__.py
baseapp_wagtail/base/rest_framework/pages/serializers.py
baseapp_wagtail/base/rest_framework/pages/views.py
baseapp_wagtail/base/rest_framework/redirects/__init__.py
baseapp_wagtail/base/rest_framework/redirects/views.py
baseapp_wagtail/base/rest_framework/sitemap/__init__.py
baseapp_wagtail/base/rest_framework/sitemap/serializers.py
baseapp_wagtail/base/rest_framework/sitemap/views.py
baseapp_wagtail/base/stream_fields/__init__.py
baseapp_wagtail/base/stream_fields/featured_image_stream_field.py
baseapp_wagtail/base/stream_fields/page_body_stream_field.py
baseapp_wagtail/base/stream_fields/standard_page_stream_block.py
baseapp_wagtail/locale/__init__.py
baseapp_wagtail/locale/utils.py
